Andromeda/__init__.py
Andromeda/build_dataset.py
Andromeda/inference.py
Andromeda/traingv2.py
andromeda_transformer-1.1.3.dist-info/LICENSE
andromeda_transformer-1.1.3.dist-info/METADATA
andromeda_transformer-1.1.3.dist-info/WHEEL
andromeda_transformer-1.1.3.dist-info/top_level.txt
andromeda_transformer-1.1.3.dist-info/RECORD
